README.md
setup.py
Apach/__init__.py
Apach/display.py
Apach.egg-info/PKG-INFO
Apach.egg-info/SOURCES.txt
Apach.egg-info/dependency_links.txt
Apach.egg-info/top_level.txt
tests/test_module1.py