Metadata-Version: 2.1
Name: Apach
Version: 0.2
Summary: GriffinX is a middleware package for real time event detection
Home-page: https://github.com/kiran-collab/Griffin-Drone-Car-Collaboration
Author: Percom@UMD
Author-email: kirandav@umich.edu
License: MIT
Classifier: Programming Language :: Python :: 3
Classifier: License :: OSI Approved :: MIT License
